.gitignore
MANIFEST.in
README.rst
setup.cfg
setup.py
docs/HISTORY.txt
docs/LICENSE.GPL
docs/LICENSE.txt
docs/MANUAL.txt
raptus/__init__.py
raptus.article.images.egg-info/PKG-INFO
raptus.article.images.egg-info/SOURCES.txt
raptus.article.images.egg-info/dependency_links.txt
raptus.article.images.egg-info/entry_points.txt
raptus.article.images.egg-info/namespace_packages.txt
raptus.article.images.egg-info/not-zip-safe
raptus.article.images.egg-info/requires.txt
raptus.article.images.egg-info/top_level.txt
raptus/article/__init__.py
raptus/article/images/__init__.py
raptus/article/images/configure.zcml
raptus/article/images/extender.py
raptus/article/images/images.py
raptus/article/images/interfaces.py
raptus/article/images/i18n/raptus.article-de.mo
raptus/article/images/i18n/raptus.article-de.po
raptus/article/images/i18n/raptus.article-fr.mo
raptus/article/images/i18n/raptus.article-fr.po
raptus/article/images/i18n/raptus.article.pot
raptus/article/images/profiles/default/metadata.xml
raptus/article/images/profiles/default/propertiestool.xml
raptus/article/images/profiles/default/types.xml
raptus/article/images/profiles/default/workflows.xml
raptus/article/images/profiles/default/types/Article.xml
raptus/article/images/tests/__init__.py
raptus/article/images/tests/base.py
raptus/article/images/tests/test_images.py
raptus/article/images/upgrades/__init__.py
raptus/article/images/upgrades/configure.zcml
raptus/article/images/upgrades/profiles.zcml
raptus/article/images/upgrades/profiles/10_to_11/propertiestool.xml