Metadata-Version: 1.1
Name: raptus.article.images
Version: 2.0b5
Summary: Provides support for adding images to articles.
Home-page: https://github.com/Raptus/raptus.article.images
Author: Raptus AG
Author-email: dev@raptus.com
License: GPL
Platform: UNKNOWN
Classifier: Programming Language :: Python
Classifier: Topic :: Software Development :: Libraries :: Python Modules
